hiquant/__init__.py
hiquant/version.py
hiquant/cli/__init__.py
hiquant/cli/cli_fund.py
hiquant/cli/cli_fundflow.py
hiquant/cli/cli_index.py
hiquant/cli/cli_indicator.py
hiquant/cli/cli_init.py
hiquant/cli/cli_main.py
hiquant/cli/cli_stock.py
hiquant/cli/cli_strategy.py
hiquant/cli/cli_trade.py
hiquant/core/__init__.py
hiquant/core/agent_human.py
hiquant/core/agent_simulated.py
hiquant/core/backtest.py
hiquant/core/conf.py
hiquant/core/data_cache.py
hiquant/core/fund.py
hiquant/core/indicator_signal.py
hiquant/core/lang.py
hiquant/core/order_cost.py
hiquant/core/portfolio.py
hiquant/core/push_base.py
hiquant/core/push_email.py
hiquant/core/push_master.py
hiquant/core/stock.py
hiquant/core/stock_market.py
hiquant/core/strategy.py
hiquant/core/trader.py
hiquant/data_source/__init__.py
hiquant/data_source/akshare_eastmoney.py
hiquant/data_source/akshare_legu.py
hiquant/data_source/akshare_sina.py
hiquant/data_source/akshare_tencent.py
hiquant/data_source/nasdaq.py
hiquant/data_source/sina.py
hiquant/data_source/yahoo.py
hiquant/indicator/__init__.py
hiquant/indicator/basic.py
hiquant/indicator/bias.py
hiquant/indicator/boll.py
hiquant/indicator/cci.py
hiquant/indicator/dma.py
hiquant/indicator/ene.py
hiquant/indicator/kdj.py
hiquant/indicator/ma.py
hiquant/indicator/macd.py
hiquant/indicator/mffi.py
hiquant/indicator/mfi.py
hiquant/indicator/obv.py
hiquant/indicator/rsi.py
hiquant/indicator/sar.py
hiquant/indicator/trix.py
hiquant/indicator/vhf.py
hiquant/indicator/wr.py
hiquant/lang_res/__init__.py
hiquant/lang_res/en.py
hiquant/lang_res/zh.py
hiquant/utils/__init__.py
hiquant/utils/args.py
hiquant/utils/datetime.py
hiquant/utils/math.py
hiquant/utils/pandas.py
hiquant/utils/symbol.py
hiquant-0.4.17.dist-info/LICENSE.txt
hiquant-0.4.17.dist-info/METADATA
hiquant-0.4.17.dist-info/WHEEL
hiquant-0.4.17.dist-info/entry_points.txt
hiquant-0.4.17.dist-info/top_level.txt
hiquant-0.4.17.dist-info/RECORD
