Metadata-Version: 2.1
Name: hiquant
Version: 0.4.17
Summary: Out-of-box python tool and framework for quantitative trading and study
Home-page: https://github.com/floatinghotpot/hiquant
Author: Liming Xie
Author-email: liming.xie@gmail.com
License: GPLv3+
Download-URL: https://github.com/floatinghotpot/hiquant
Keywords: stock,fund,finance,spider,quant,quantitative,investment,trading,algotrading,data
Platform: any
Classifier: Development Status :: 4 - Beta
Classifier: Intended Audience :: Developers
Classifier: Intended Audience :: Financial and Insurance Industry
Classifier: Topic :: Software Development
Classifier: Topic :: Office/Business :: Financial
Classifier: License :: OSI Approved :: GNU General Public License v3 or later (GPLv3+)
Classifier: Programming Language :: Python :: 3
Classifier: Programming Language :: Python :: 3.7
Classifier: Operating System :: OS Independent
Requires-Python: >=3.7
License-File: LICENSE.txt
Requires-Dist: requests (>=2.25.1)
Requires-Dist: pandas (>=1.2.4)
Requires-Dist: akshare (==0.9.95)
Requires-Dist: tabulate (>=0.8.9)
Requires-Dist: matplotlib (>=3.4.1)
Requires-Dist: mplfinance (>=0.12.7a17)
